{
  "id": "91abf438-d115-4028-b806-771ee5b26a4e",
  "prevId": "00000000-0000-0000-0000-000000000000",
  "version": "7",
  "dialect": "postgresql",
  "tables": {
    "public.accounts": {
      "name": "accounts",
      "schema": "",
      "columns": {
        "id": {
          "name": "id",
          "type": "text",
          "primaryKey": true,
          "notNull": true
        },
        "account_id": {
          "name": "account_id",
          "type": "text",
          "primaryKey": false,
          "notNull": true
        },
        "provider_id": {
          "name": "provider_id",
          "type": "text",
          "primaryKey": false,
          "notNull": true
        },
        "user_id": {
          "name": "user_id",
          "type": "text",
          "primaryKey": false,
          "notNull": true
        },
        "access_token": {
          "name": "access_token",
          "type": "text",
          "primaryKey": false,
          "notNull": false
        },
        "refresh_token": {
          "name": "refresh_token",
          "type": "text",
          "primaryKey": false,
          "notNull": false
        },
        "id_token": {
          "name": "id_token",
          "type": "text",
          "primaryKey": false,
          "notNull": false
        },
        "access_token_expires_at": {
          "name": "access_token_expires_at",
          "type": "timestamp",
          "primaryKey": false,
          "notNull": false
        },
        "refresh_token_expires_at": {
          "name": "refresh_token_expires_at",
          "type": "timestamp",
          "primaryKey": false,
          "notNull": false
        },
        "scope": {
          "name": "scope",
          "type": "text",
          "primaryKey": false,
          "notNull": false
        },
        "password": {
          "name": "password",
          "type": "text",
          "primaryKey": false,
          "notNull": false
        },
        "created_at": {
          "name": "created_at",
          "type": "timestamp",
          "primaryKey": false,
          "notNull": true,
          "default": "now()"
        },
        "updated_at": {
          "name": "updated_at",
          "type": "timestamp",
          "primaryKey": false,
          "notNull": true
        }
      },
      "indexes": {},
      "foreignKeys": {
        "accounts_user_id_users_id_fk": {
          "name": "accounts_user_id_users_id_fk",
          "tableFrom": "accounts",
          "tableTo": "users",
          "columnsFrom": [
            "user_id"
          ],
          "columnsTo": [
            "id"
          ],
          "onDelete": "cascade",
          "onUpdate": "no action"
        }
      },
      "compositePrimaryKeys": {},
      "uniqueConstraints": {},
      "policies": {},
      "checkConstraints": {},
      "isRLSEnabled": false
    },
    "public.sessions": {
      "name": "sessions",
      "schema": "",
      "columns": {
        "id": {
          "name": "id",
          "type": "text",
          "primaryKey": true,
          "notNull": true
        },
        "expires_at": {
          "name": "expires_at",
          "type": "timestamp",
          "primaryKey": false,
          "notNull": true
        },
        "token": {
          "name": "token",
          "type": "text",
          "primaryKey": false,
          "notNull": true
        },
        "created_at": {
          "name": "created_at",
          "type": "timestamp",
          "primaryKey": false,
          "notNull": true,
          "default": "now()"
        },
        "updated_at": {
          "name": "updated_at",
          "type": "timestamp",
          "primaryKey": false,
          "notNull": true
        },
        "ip_address": {
          "name": "ip_address",
          "type": "text",
          "primaryKey": false,
          "notNull": false
        },
        "user_agent": {
          "name": "user_agent",
          "type": "text",
          "primaryKey": false,
          "notNull": false
        },
        "user_id": {
          "name": "user_id",
          "type": "text",
          "primaryKey": false,
          "notNull": true
        }
      },
      "indexes": {},
      "foreignKeys": {
        "sessions_user_id_users_id_fk": {
          "name": "sessions_user_id_users_id_fk",
          "tableFrom": "sessions",
          "tableTo": "users",
          "columnsFrom": [
            "user_id"
          ],
          "columnsTo": [
            "id"
          ],
          "onDelete": "cascade",
          "onUpdate": "no action"
        }
      },
      "compositePrimaryKeys": {},
      "uniqueConstraints": {
        "sessions_token_unique": {
          "name": "sessions_token_unique",
          "nullsNotDistinct": false,
          "columns": [
            "token"
          ]
        }
      },
      "policies": {},
      "checkConstraints": {},
      "isRLSEnabled": false
    },
    "public.users": {
      "name": "users",
      "schema": "",
      "columns": {
        "id": {
          "name": "id",
          "type": "serial",
          "primaryKey": true,
          "notNull": true
        },
        "username": {
          "name": "username",
          "type": "text",
          "primaryKey": false,
          "notNull": true
        },
        "password_hash": {
          "name": "password_hash",
          "type": "text",
          "primaryKey": false,
          "notNull": true
        },
        "name": {
          "name": "name",
          "type": "text",
          "primaryKey": false,
          "notNull": true
        },
        "first_name": {
          "name": "first_name",
          "type": "text",
          "primaryKey": false,
          "notNull": false
        },
        "last_name": {
          "name": "last_name",
          "type": "text",
          "primaryKey": false,
          "notNull": false
        },
        "internal_numbers": {
          "name": "internal_numbers",
          "type": "text",
          "primaryKey": false,
          "notNull": false
        },
        "mobile_numbers": {
          "name": "mobile_numbers",
          "type": "text",
          "primaryKey": false,
          "notNull": false
        },
        "created_at": {
          "name": "created_at",
          "type": "text",
          "primaryKey": false,
          "notNull": true
        },
        "is_active": {
          "name": "is_active",
          "type": "boolean",
          "primaryKey": false,
          "notNull": false,
          "default": true
        },
        "telegram_chat_id": {
          "name": "telegram_chat_id",
          "type": "text",
          "primaryKey": false,
          "notNull": false
        },
        "telegram_connect_token": {
          "name": "telegram_connect_token",
          "type": "text",
          "primaryKey": false,
          "notNull": false
        },
        "telegram_daily_report": {
          "name": "telegram_daily_report",
          "type": "boolean",
          "primaryKey": false,
          "notNull": false,
          "default": false
        },
        "telegram_manager_report": {
          "name": "telegram_manager_report",
          "type": "boolean",
          "primaryKey": false,
          "notNull": false,
          "default": false
        },
        "telegram_weekly_report": {
          "name": "telegram_weekly_report",
          "type": "boolean",
          "primaryKey": false,
          "notNull": false,
          "default": false
        },
        "telegram_monthly_report": {
          "name": "telegram_monthly_report",
          "type": "boolean",
          "primaryKey": false,
          "notNull": false,
          "default": false
        },
        "telegram_skip_weekends": {
          "name": "telegram_skip_weekends",
          "type": "boolean",
          "primaryKey": false,
          "notNull": false,
          "default": false
        },
        "max_chat_id": {
          "name": "max_chat_id",
          "type": "text",
          "primaryKey": false,
          "notNull": false
        },
        "max_connect_token": {
          "name": "max_connect_token",
          "type": "text",
          "primaryKey": false,
          "notNull": false
        },
        "max_daily_report": {
          "name": "max_daily_report",
          "type": "boolean",
          "primaryKey": false,
          "notNull": false,
          "default": false
        },
        "max_manager_report": {
          "name": "max_manager_report",
          "type": "boolean",
          "primaryKey": false,
          "notNull": false,
          "default": false
        },
        "email": {
          "name": "email",
          "type": "text",
          "primaryKey": false,
          "notNull": false
        },
        "email_daily_report": {
          "name": "email_daily_report",
          "type": "boolean",
          "primaryKey": false,
          "notNull": false,
          "default": false
        },
        "email_weekly_report": {
          "name": "email_weekly_report",
          "type": "boolean",
          "primaryKey": false,
          "notNull": false,
          "default": false
        },
        "email_monthly_report": {
          "name": "email_monthly_report",
          "type": "boolean",
          "primaryKey": false,
          "notNull": false,
          "default": false
        },
        "filter_exclude_answering_machine": {
          "name": "filter_exclude_answering_machine",
          "type": "boolean",
          "primaryKey": false,
          "notNull": false,
          "default": false
        },
        "filter_min_duration": {
          "name": "filter_min_duration",
          "type": "integer",
          "primaryKey": false,
          "notNull": false,
          "default": 0
        },
        "filter_min_replicas": {
          "name": "filter_min_replicas",
          "type": "integer",
          "primaryKey": false,
          "notNull": false,
          "default": 0
        },
        "report_include_call_summaries": {
          "name": "report_include_call_summaries",
          "type": "boolean",
          "primaryKey": false,
          "notNull": false,
          "default": false
        },
        "report_detailed": {
          "name": "report_detailed",
          "type": "boolean",
          "primaryKey": false,
          "notNull": false,
          "default": false
        },
        "report_include_avg_value": {
          "name": "report_include_avg_value",
          "type": "boolean",
          "primaryKey": false,
          "notNull": false,
          "default": false
        },
        "report_include_avg_rating": {
          "name": "report_include_avg_rating",
          "type": "boolean",
          "primaryKey": false,
          "notNull": false,
          "default": false
        },
        "report_managed_user_ids": {
          "name": "report_managed_user_ids",
          "type": "text",
          "primaryKey": false,
          "notNull": false
        },
        "kpi_base_salary": {
          "name": "kpi_base_salary",
          "type": "real",
          "primaryKey": false,
          "notNull": false,
          "default": 0
        },
        "kpi_target_bonus": {
          "name": "kpi_target_bonus",
          "type": "real",
          "primaryKey": false,
          "notNull": false,
          "default": 0
        },
        "kpi_target_talk_time_minutes": {
          "name": "kpi_target_talk_time_minutes",
          "type": "integer",
          "primaryKey": false,
          "notNull": false,
          "default": 0
        }
      },
      "indexes": {
        "users_username_idx": {
          "name": "users_username_idx",
          "columns": [
            {
              "expression": "username",
              "isExpression": false,
              "asc": true,
              "nulls": "last"
            }
          ],
          "isUnique": false,
          "concurrently": false,
          "method": "btree",
          "with": {}
        },
        "users_is_active_idx": {
          "name": "users_is_active_idx",
          "columns": [
            {
              "expression": "is_active",
              "isExpression": false,
              "asc": true,
              "nulls": "last"
            }
          ],
          "isUnique": false,
          "concurrently": false,
          "method": "btree",
          "with": {}
        }
      },
      "foreignKeys": {},
      "compositePrimaryKeys": {},
      "uniqueConstraints": {
        "users_username_unique": {
          "name": "users_username_unique",
          "nullsNotDistinct": false,
          "columns": [
            "username"
          ]
        }
      },
      "policies": {},
      "checkConstraints": {},
      "isRLSEnabled": false
    },
    "public.verifications": {
      "name": "verifications",
      "schema": "",
      "columns": {
        "id": {
          "name": "id",
          "type": "text",
          "primaryKey": true,
          "notNull": true
        },
        "identifier": {
          "name": "identifier",
          "type": "text",
          "primaryKey": false,
          "notNull": true
        },
        "value": {
          "name": "value",
          "type": "text",
          "primaryKey": false,
          "notNull": true
        },
        "expires_at": {
          "name": "expires_at",
          "type": "timestamp",
          "primaryKey": false,
          "notNull": true
        },
        "created_at": {
          "name": "created_at",
          "type": "timestamp",
          "primaryKey": false,
          "notNull": true,
          "default": "now()"
        },
        "updated_at": {
          "name": "updated_at",
          "type": "timestamp",
          "primaryKey": false,
          "notNull": true,
          "default": "now()"
        }
      },
      "indexes": {},
      "foreignKeys": {},
      "compositePrimaryKeys": {},
      "uniqueConstraints": {},
      "policies": {},
      "checkConstraints": {},
      "isRLSEnabled": false
    },
    "public.activity_log": {
      "name": "activity_log",
      "schema": "",
      "columns": {
        "id": {
          "name": "id",
          "type": "serial",
          "primaryKey": true,
          "notNull": true
        },
        "timestamp": {
          "name": "timestamp",
          "type": "text",
          "primaryKey": false,
          "notNull": true
        },
        "level": {
          "name": "level",
          "type": "text",
          "primaryKey": false,
          "notNull": true
        },
        "message": {
          "name": "message",
          "type": "text",
          "primaryKey": false,
          "notNull": true
        },
        "actor": {
          "name": "actor",
          "type": "text",
          "primaryKey": false,
          "notNull": true
        }
      },
      "indexes": {
        "activity_log_timestamp_idx": {
          "name": "activity_log_timestamp_idx",
          "columns": [
            {
              "expression": "timestamp",
              "isExpression": false,
              "asc": true,
              "nulls": "last"
            }
          ],
          "isUnique": false,
          "concurrently": false,
          "method": "btree",
          "with": {}
        }
      },
      "foreignKeys": {},
      "compositePrimaryKeys": {},
      "uniqueConstraints": {},
      "policies": {},
      "checkConstraints": {},
      "isRLSEnabled": false
    },
    "public.call_evaluations": {
      "name": "call_evaluations",
      "schema": "",
      "columns": {
        "id": {
          "name": "id",
          "type": "serial",
          "primaryKey": true,
          "notNull": true
        },
        "call_id": {
          "name": "call_id",
          "type": "integer",
          "primaryKey": false,
          "notNull": true
        },
        "is_quality_analyzable": {
          "name": "is_quality_analyzable",
          "type": "boolean",
          "primaryKey": false,
          "notNull": false,
          "default": true
        },
        "not_analyzable_reason": {
          "name": "not_analyzable_reason",
          "type": "text",
          "primaryKey": false,
          "notNull": false
        },
        "value_score": {
          "name": "value_score",
          "type": "integer",
          "primaryKey": false,
          "notNull": false
        },
        "value_explanation": {
          "name": "value_explanation",
          "type": "text",
          "primaryKey": false,
          "notNull": false
        },
        "manager_score": {
          "name": "manager_score",
          "type": "integer",
          "primaryKey": false,
          "notNull": false
        },
        "manager_feedback": {
          "name": "manager_feedback",
          "type": "text",
          "primaryKey": false,
          "notNull": false
        },
        "manager_breakdown": {
          "name": "manager_breakdown",
          "type": "text",
          "primaryKey": false,
          "notNull": false
        },
        "manager_recommendations": {
          "name": "manager_recommendations",
          "type": "text",
          "primaryKey": false,
          "notNull": false
        },
        "created_at": {
          "name": "created_at",
          "type": "text",
          "primaryKey": false,
          "notNull": true
        }
      },
      "indexes": {
        "call_evaluations_call_id_idx": {
          "name": "call_evaluations_call_id_idx",
          "columns": [
            {
              "expression": "call_id",
              "isExpression": false,
              "asc": true,
              "nulls": "last"
            }
          ],
          "isUnique": false,
          "concurrently": false,
          "method": "btree",
          "with": {}
        },
        "call_evaluations_value_score_idx": {
          "name": "call_evaluations_value_score_idx",
          "columns": [
            {
              "expression": "value_score",
              "isExpression": false,
              "asc": true,
              "nulls": "last"
            }
          ],
          "isUnique": false,
          "concurrently": false,
          "method": "btree",
          "with": {}
        }
      },
      "foreignKeys": {
        "call_evaluations_call_id_calls_id_fk": {
          "name": "call_evaluations_call_id_calls_id_fk",
          "tableFrom": "call_evaluations",
          "tableTo": "calls",
          "columnsFrom": [
            "call_id"
          ],
          "columnsTo": [
            "id"
          ],
          "onDelete": "cascade",
          "onUpdate": "no action"
        }
      },
      "compositePrimaryKeys": {},
      "uniqueConstraints": {
        "call_evaluations_call_id_unique": {
          "name": "call_evaluations_call_id_unique",
          "nullsNotDistinct": false,
          "columns": [
            "call_id"
          ]
        }
      },
      "policies": {},
      "checkConstraints": {},
      "isRLSEnabled": false
    },
    "public.calls": {
      "name": "calls",
      "schema": "",
      "columns": {
        "id": {
          "name": "id",
          "type": "serial",
          "primaryKey": true,
          "notNull": true
        },
        "filename": {
          "name": "filename",
          "type": "text",
          "primaryKey": false,
          "notNull": false
        },
        "number": {
          "name": "number",
          "type": "text",
          "primaryKey": false,
          "notNull": false
        },
        "timestamp": {
          "name": "timestamp",
          "type": "text",
          "primaryKey": false,
          "notNull": true
        },
        "name": {
          "name": "name",
          "type": "text",
          "primaryKey": false,
          "notNull": false
        },
        "duration": {
          "name": "duration",
          "type": "integer",
          "primaryKey": false,
          "notNull": false
        },
        "direction": {
          "name": "direction",
          "type": "text",
          "primaryKey": false,
          "notNull": false
        },
        "status": {
          "name": "status",
          "type": "text",
          "primaryKey": false,
          "notNull": false
        },
        "size_bytes": {
          "name": "size_bytes",
          "type": "integer",
          "primaryKey": false,
          "notNull": false
        },
        "internal_number": {
          "name": "internal_number",
          "type": "text",
          "primaryKey": false,
          "notNull": false
        },
        "source": {
          "name": "source",
          "type": "text",
          "primaryKey": false,
          "notNull": false
        },
        "customer_name": {
          "name": "customer_name",
          "type": "text",
          "primaryKey": false,
          "notNull": false
        }
      },
      "indexes": {
        "calls_timestamp_idx": {
          "name": "calls_timestamp_idx",
          "columns": [
            {
              "expression": "timestamp",
              "isExpression": false,
              "asc": true,
              "nulls": "last"
            }
          ],
          "isUnique": false,
          "concurrently": false,
          "method": "btree",
          "with": {}
        },
        "calls_internal_number_idx": {
          "name": "calls_internal_number_idx",
          "columns": [
            {
              "expression": "internal_number",
              "isExpression": false,
              "asc": true,
              "nulls": "last"
            }
          ],
          "isUnique": false,
          "concurrently": false,
          "method": "btree",
          "with": {}
        }
      },
      "foreignKeys": {},
      "compositePrimaryKeys": {},
      "uniqueConstraints": {
        "calls_filename_unique": {
          "name": "calls_filename_unique",
          "nullsNotDistinct": false,
          "columns": [
            "filename"
          ]
        }
      },
      "policies": {},
      "checkConstraints": {},
      "isRLSEnabled": false
    },
    "public.prompts": {
      "name": "prompts",
      "schema": "",
      "columns": {
        "id": {
          "name": "id",
          "type": "serial",
          "primaryKey": true,
          "notNull": true
        },
        "key": {
          "name": "key",
          "type": "text",
          "primaryKey": false,
          "notNull": true
        },
        "value": {
          "name": "value",
          "type": "text",
          "primaryKey": false,
          "notNull": true
        },
        "description": {
          "name": "description",
          "type": "text",
          "primaryKey": false,
          "notNull": false
        },
        "updated_at": {
          "name": "updated_at",
          "type": "text",
          "primaryKey": false,
          "notNull": false
        }
      },
      "indexes": {
        "prompts_key_idx": {
          "name": "prompts_key_idx",
          "columns": [
            {
              "expression": "key",
              "isExpression": false,
              "asc": true,
              "nulls": "last"
            }
          ],
          "isUnique": false,
          "concurrently": false,
          "method": "btree",
          "with": {}
        }
      },
      "foreignKeys": {},
      "compositePrimaryKeys": {},
      "uniqueConstraints": {
        "prompts_key_unique": {
          "name": "prompts_key_unique",
          "nullsNotDistinct": false,
          "columns": [
            "key"
          ]
        }
      },
      "policies": {},
      "checkConstraints": {},
      "isRLSEnabled": false
    },
    "public.transcripts": {
      "name": "transcripts",
      "schema": "",
      "columns": {
        "id": {
          "name": "id",
          "type": "serial",
          "primaryKey": true,
          "notNull": true
        },
        "call_id": {
          "name": "call_id",
          "type": "integer",
          "primaryKey": false,
          "notNull": true
        },
        "text": {
          "name": "text",
          "type": "text",
          "primaryKey": false,
          "notNull": false
        },
        "raw_text": {
          "name": "raw_text",
          "type": "text",
          "primaryKey": false,
          "notNull": false
        },
        "title": {
          "name": "title",
          "type": "text",
          "primaryKey": false,
          "notNull": false
        },
        "sentiment": {
          "name": "sentiment",
          "type": "text",
          "primaryKey": false,
          "notNull": false
        },
        "confidence": {
          "name": "confidence",
          "type": "real",
          "primaryKey": false,
          "notNull": false
        },
        "summary": {
          "name": "summary",
          "type": "text",
          "primaryKey": false,
          "notNull": false
        },
        "size_kb": {
          "name": "size_kb",
          "type": "integer",
          "primaryKey": false,
          "notNull": false
        },
        "caller_name": {
          "name": "caller_name",
          "type": "text",
          "primaryKey": false,
          "notNull": false
        },
        "call_type": {
          "name": "call_type",
          "type": "text",
          "primaryKey": false,
          "notNull": false
        },
        "call_topic": {
          "name": "call_topic",
          "type": "text",
          "primaryKey": false,
          "notNull": false
        }
      },
      "indexes": {
        "transcripts_call_id_idx": {
          "name": "transcripts_call_id_idx",
          "columns": [
            {
              "expression": "call_id",
              "isExpression": false,
              "asc": true,
              "nulls": "last"
            }
          ],
          "isUnique": false,
          "concurrently": false,
          "method": "btree",
          "with": {}
        }
      },
      "foreignKeys": {
        "transcripts_call_id_calls_id_fk": {
          "name": "transcripts_call_id_calls_id_fk",
          "tableFrom": "transcripts",
          "tableTo": "calls",
          "columnsFrom": [
            "call_id"
          ],
          "columnsTo": [
            "id"
          ],
          "onDelete": "cascade",
          "onUpdate": "no action"
        }
      },
      "compositePrimaryKeys": {},
      "uniqueConstraints": {},
      "policies": {},
      "checkConstraints": {},
      "isRLSEnabled": false
    },
    "public.posts": {
      "name": "posts",
      "schema": "",
      "columns": {
        "id": {
          "name": "id",
          "type": "uuid",
          "primaryKey": true,
          "notNull": true,
          "default": "gen_random_uuid()"
        },
        "title": {
          "name": "title",
          "type": "varchar(256)",
          "primaryKey": false,
          "notNull": true
        },
        "content": {
          "name": "content",
          "type": "text",
          "primaryKey": false,
          "notNull": true
        },
        "created_at": {
          "name": "created_at",
          "type": "timestamp",
          "primaryKey": false,
          "notNull": true,
          "default": "now()"
        },
        "updated_at": {
          "name": "updated_at",
          "type": "timestamp with time zone",
          "primaryKey": false,
          "notNull": false
        }
      },
      "indexes": {},
      "foreignKeys": {},
      "compositePrimaryKeys": {},
      "uniqueConstraints": {},
      "policies": {},
      "checkConstraints": {},
      "isRLSEnabled": false
    }
  },
  "enums": {},
  "schemas": {},
  "sequences": {},
  "roles": {},
  "policies": {},
  "views": {},
  "_meta": {
    "columns": {},
    "schemas": {},
    "tables": {}
  }
}