{
  "version": "7",
  "dialect": "postgresql",
  "entries": [
    {
      "idx": 0,
      "version": "7",
      "when": 1775369524115,
      "tag": "0000_loving_the_liberteens",
      "breakpoints": true
    },
    {
      "idx": 1,
      "version": "7",
      "when": 1775553921106,
      "tag": "0001_messy_giant_girl",
      "breakpoints": true
    },
    {
      "idx": 2,
      "version": "7",
      "when": 1775642964010,
      "tag": "0002_abnormal_ozymandias",
      "breakpoints": true
    },
    {
      "idx": 3,
      "version": "7",
      "when": 1775813400958,
      "tag": "0003_useful_captain_midlands",
      "breakpoints": true
    },
    {
      "idx": 4,
      "version": "7",
      "when": 1776086136604,
      "tag": "0004_fuzzy_vulcan",
      "breakpoints": true
    },
    {
      "idx": 5,
      "version": "7",
      "when": 1776087827129,
      "tag": "0005_naive_brother_voodoo",
      "breakpoints": true
    }
  ]
}
